Metadata-Version: 2.1
Name: libpythonpro-wp
Version: 0.2
Summary: Modulo para exemplificar construcao de projetos Python no curso PyTools
Home-page: https://github.com/rwollensc/libpythonpro
Author: Rodrigo Pereira
Author-email: rodrigowollensc@gmail.com
License:                     GNU AFFERO GENERAL PUBLIC LICENSE
Platform: UNKNOWN
Classifier: Development Status :: 2 - Pre-Alpha
Classifier: Environment :: Console
Classifier: Intended Audience :: Developers
Classifier: License :: OSI Approved :: GNU Affero General Public License v3 or later (AGPLv3+)
Classifier: Operating System :: OS Independent
Classifier: Programming Language :: Python
Classifier: Framework :: Pytest
License-File: LICENSE
